{"locale": "hi", "name": "Hindi", "native": "हिन्दी", "region": "IN", "version": "20260116203418", "files_merged": 16, "total_keys": 583, "translations": {"landing": {"philosophy": {"notNoCode": {"flytoApproach": {"item1": {"description": "देखें कि हर चरण पर क्या होता है", "title": "निरीक्षण योग्य"}, "item2": {"description": "पता करें कि क्यों और कहां चीज़ें विफल हुईं", "title": "डीबग करने योग्य"}, "item3": {"description": "ओपन सोर्स कोर, कोई वेंडर लॉक-इन नहीं", "title": "खुला"}, "item4": {"description": "आपके व्यवसाय के बढ़ने के साथ स्केल होता है", "title": "विस्तार योग्य"}, "title": "Flyto2 दृष्टिकोण"}, "noCodePromise": {"item1": {"description": "कुछ टूटने तक सरल दिखता है", "title": "छिपी जटिलता"}, "item2": {"description": "देख नहीं सकते कि वास्तव में क्या विफल हुआ", "title": "ब्लैक बॉक्स ऑपरेशन"}, "item3": {"description": "वेंडर के एब्स्ट्रैक्शन में फंसे", "title": "वेंडर लॉक-इन"}, "item4": {"description": "डिफ़ॉल्ट से आगे बढ़ने पर अटके", "title": "सीमित विस्तारयोग्यता"}, "title": "नो-कोड वादा"}, "subtitle": "नो-कोड सादगी का वादा करता है। लेकिन सरल हमेशा सही जवाब नहीं है।", "title": "हम शुद्ध नो-कोड टूल क्यों नहीं हैं"}, "coreBeliefs": {"principle1": {"description": "सबसे अच्छा ऑटोमेशन मनुष्यों को प्रतिस्थापित नहीं करता - यह उन्हें बढ़ाता है। हम जो भी सुविधा डिज़ाइन करते हैं वह मनुष्यों को नियंत्रण में रखती है।", "quote": "नियंत्रण आपके हाथों में रहता है", "title": "मानवीय निरीक्षण एक सुविधा है"}, "principle2": {"description": "अगर आप निरीक्षण नहीं कर सकते कि क्या हुआ, आप विश्वास नहीं कर सकते। हर क्रिया में लॉग, स्क्रीनशॉट और ऑडिट ट्रेल हैं।", "quote": "पारदर्शिता विश्वास बनाती है", "title": "वर्कफ़्लो सत्यापन योग्य होने चाहिए"}, "principle3": {"description": "आपका डेटा आपके नेटवर्क से बाहर नहीं जाना चाहिए। कोई क्लाउड निर्भरता नहीं, कोई डेटा फ़ोनिंग होम नहीं, पूर्ण नियंत्रण।", "quote": "आपका डेटा, आपके नियम", "title": "ऑफ़लाइन-फर्स्ट, हमेशा"}, "subtitle": "ये सिद्धांत हमारे हर डिज़ाइन निर्णय को निर्देशित करते हैं।", "title": "हमारी मूल मान्यताएं"}, "humanSteps": {"belief1": {"description": "हर Flyto2 वर्कफ़्लो किसी भी चरण पर रुक, निरीक्षण और फिर से शुरू हो सकता है।", "title": "सबसे खतरनाक ऑटोमेशन वह है जिसे आप रोक नहीं सकते"}, "belief2": {"description": "मानवीय अनुमोदन चरण प्रथम श्रेणी के नागरिक हैं, किसी भी अन्य चरण की तरह।", "title": "अनुमोदन बिल्ट-इन होने चाहिए, बोल्ट-ऑन नहीं"}, "belief3": {"description": "चेकपॉइंट पर वापस जाएं, समस्या ठीक करें, जारी रखें। शुरू से शुरू करने की ज़रूरत नहीं।", "title": "गलतियां विनाशकारी नहीं होनी चाहिए"}, "belief4": {"description": "हर क्रिया, हर निर्णय, हर अनुमोदन लॉग और टाइमस्टैम्प किया जाता है।", "title": "ऑडिट ट्रेल वैकल्पिक नहीं हैं"}, "title": "मानवीय चरण एक मूल सुविधा क्यों हैं"}, "finalStatement": {"description": "Flyto2 मुफ़्त में आज़माएं और देखें कि मानवीय निरीक्षण क्यों मायने रखता है।", "title": "अंतर अनुभव करने के लिए तैयार?", "cta": "योजनाएं देखें"}, "result": {"step1": {"description": "प्रदर्शन द्वारा अपना वर्कफ़्लो रिकॉर्ड करें", "title": "रिकॉर्ड"}, "step2": {"description": "पहले एक आइटम चलाएं, पुष्टि करें कि यह सही है", "title": "सत्यापित करें"}, "step3": {"description": "प्रत्येक चरण के परिणामों की समीक्षा करें", "title": "समीक्षा करें"}, "step4": {"description": "विश्वास के साथ बैच में प्रोसेस करें", "title": "स्केल करें"}, "title": "परिणाम"}, "hero": {"description": "मानवीय निरीक्षण एक सीमा नहीं है - यह एक सुविधा है। सत्यापन योग्य वर्कफ़्लो बोझ नहीं हैं - वे नींव हैं।", "title": "हमने Flyto2 को अलग तरीके से क्यों बनाया"}, "breadcrumb": "दर्शन", "quote": "ऑटोमेशन का लक्ष्य मनुष्यों को बदलना नहीं है। यह मनुष्यों को उस पर ध्यान केंद्रित करने के लिए मुक्त करना है जो वास्तव में मानवीय बुद्धि की आवश्यकता है।"}, "about": {"values": {"humanOversight": {"description": "हर ऑटोमेशन को रोका, निरीक्षण और समायोजित किया जा सकता है। आप हमेशा नियंत्रण में हैं।", "title": "मानवीय निरीक्षण"}, "localFirst": {"description": "आपका डेटा आपकी मशीन पर रहता है। कोई छिपे हुए क्लाउड कॉल नहीं, कोई डेटा हार्वेस्टिंग नहीं।", "title": "लोकल-फर्स्ट"}, "openSource": {"description": "हमारा कोर ओपन सोर्स है। आप अपनी मशीन पर चलने वाले कोड की हर पंक्ति का निरीक्षण कर सकते हैं।", "title": "ओपन सोर्स"}, "verifiable": {"description": "हर क्रिया लॉग और ट्रेसेबल है। देखें कि वास्तव में क्या हुआ और क्यों।", "title": "सत्यापन योग्य"}, "title": "हमारे मूल्य"}, "stats": {"platformsSupported": {"number": "3", "label": "प्लेटफ़ॉर्म"}, "offlineCapable": {"number": "100%", "label": "ऑफ़लाइन काम करता है"}, "atomicModules": {"number": "384+", "label": "एटॉमिक मॉड्यूल"}, "openSource": {"number": "100%", "label": "ओपन सोर्स"}}, "openSource": {"viewOnGithub": "GitHub पर देखें", "description": "हमारा कोर इंजन ओपन सोर्स है, जिससे कोई भी कोडबेस का निरीक्षण, संशोधन और योगदान कर सकता है।", "pypiPackage": "PyPI पर उपलब्ध", "badge": "ओपन सोर्स", "title": "खुले में निर्मित"}, "technology": {"description": "आधुनिक, विश्वसनीय तकनीकों के साथ निर्मित", "playwright": "ब्राउज़र ऑटोमेशन", "docker": "कंटेनराइज़ेशन", "python": "बैकएंड इंजन", "sqlite": "लोकल डेटाबेस", "title": "हमारा टेक्नोलॉजी स्टैक", "vuejs": "फ़्रंटएंड फ़्रेमवर्क"}, "contact": {"description": "सवाल हैं या एंटरप्राइज़ सपोर्ट चाहिए? हम मदद के लिए यहां हैं।", "viewPricing": "मूल्य देखें", "title": "संपर्क करें"}, "mission": {"description": "ऑटोमेशन को लोगों को सशक्त बनाना चाहिए, उन्हें बदलना नहीं। हम उन टूल्स में विश्वास करते हैं जो मानवीय क्षमताओं को बढ़ाते हैं जबकि आपको नियंत्रण में रखते हैं।", "statement": "पारदर्शिता और मानवीय निरीक्षण बनाए रखते हुए शक्तिशाली ऑटोमेशन को सभी के लिए सुलभ बनाना।", "title": "हमारा मिशन"}, "hero": {"description": "हम वर्कफ़्लो ऑटोमेशन का भविष्य बना रहे हैं - पारदर्शी, सत्यापन योग्य, और मानव-केंद्रित।", "title": "Flyto2 के बारे में"}}, "product": {"comparison": {"builtinValidation": "बिल्ट-इन डेटा वैलिडेशन", "titleHighlight": "ऑटोमेशन टूल्स", "traditionalRpa": "पारंपरिक RPA", "humanApproval": "मानवीय अनुमोदन चरण", "detailedBtn": "विस्तृत तुलना देखें", "pauseResume": "वर्कफ़्लो में रोकें और फिर शुरू करें", "auditTrail": "पूर्ण ऑडिट ट्रेल", "openSource": "ओपन सोर्स कोर", "rollback": "चेकपॉइंट पर रोलबैक", "feature": "सुविधा", "offline": "100% ऑफ़लाइन ऑपरेशन", "partial": "आंशिक", "title": "Flyto2 बनाम पारंपरिक"}, "problem": {"allOrNothing": {"title": "सब-या-कुछ-नहीं निष्पादन", "desc": "पारंपरिक RPA पूर्णता या क्रैश तक चलता है। कोई बीच का रास्ता नहीं। 1,000 रिकॉर्ड प्रोसेस करते समय, आपको पता नहीं चलेगा कि कुछ गलत है जब तक नुकसान पूरे डेटासेट में फैल न जाए।"}, "noApproval": {"title": "कोई अनुमोदन वर्कफ़्लो नहीं", "desc": "अधिकांश RPA टूल्स मानवीय अनुमोदन के लिए नहीं रुक सकते। विनियमित उद्योगों में जहां हर क्रिया को सत्यापन की आवश्यकता होती है, यह महत्वपूर्ण प्रक्रियाओं को स्वचालित करना असंभव बनाता है।"}, "validation": {"title": "वैलिडेशन बाद में सोचने का काम है", "desc": "पारंपरिक RPA में डेटा वैलिडेशन बोल्ट-ऑन है, बिल्ट-इन नहीं। जब डेटा अपेक्षाओं से मेल नहीं खाता, वर्कफ़्लो चुपचाप विफल हो जाते हैं, बिना स्पष्ट रिकवरी पथ के दूषित रिकॉर्ड छोड़ते हैं।"}, "titleHighlight": "हल नहीं कर सकता", "cloud": {"title": "क्लाउड निर्भरता", "desc": "एंटरप्राइज़ डेटा अक्सर आपके नेटवर्क से बाहर नहीं जा सकता। अधिकांश आधुनिक ऑटोमेशन प्लेटफ़ॉर्म क्लाउड कनेक्टिविटी की आवश्यकता होती है, जो उन्हें एयर-गैप्ड वातावरण या सख्त अनुपालन आवश्यकताओं के लिए अनुपयुक्त बनाता है।"}, "subtitle": "अधिकांश ऑटोमेशन टूल्स में एक मौलिक दोष है: वे मानवीय हस्तक्षेप के बिना चलने के लिए डिज़ाइन किए गए हैं।", "title": "समस्याएं जो पारंपरिक RPA"}, "validation": {"titleHighlight": "कोर इंजन में", "step1": {"title": "इनपुट वैलिडेशन", "desc": "हर मॉड्यूल निष्पादन से पहले इनपुट को मान्य करता है। गलत डेटा प्रकार? गायब फ़ील्ड? वर्कफ़्लो स्पष्ट त्रुटि संदेशों के साथ तुरंत रुक जाता है।"}, "step2": {"title": "स्कीमा एनफोर्समेंट", "desc": "मॉड्यूल के बीच बहने वाला डेटा परिभाषित स्कीमा के अनुरूप होना चाहिए। कोई साइलेंट टाइप कोर्शन नहीं, कोई 'कभी-कभी काम करता है' परिदृश्य नहीं।"}, "step3": {"title": "आउटपुट वैलिडेशन", "desc": "प्रत्येक चरण पूरा होने के बाद, आउटपुट अपेक्षित स्कीमा के खिलाफ मान्य होते हैं। अगर कुछ गड़बड़ है, आपको पता चलता है इससे पहले कि यह डाउनस्ट्रीम प्रक्रियाओं को प्रभावित करे।"}, "step4": {"title": "चेकपॉइंट निर्माण", "desc": "कॉन्फ़िगर करने योग्य अंतराल पर, Flyto2 चेकपॉइंट बनाता है। अगर वैलिडेशन बाद में विफल होता है, आप अंतिम ज्ञात अच्छी स्थिति पर वापस जा सकते हैं।"}, "subtitle": "अधिकांश ऑटोमेशन विफलताएं लॉजिक त्रुटियां नहीं हैं - वे डेटा त्रुटियां हैं जो समय पर नहीं पकड़ी गईं।", "title": "वैलिडेशन को क्यों बनाना चाहिए"}, "solution": {"approval": {"title": "मानवीय अनुमोदन चरण", "desc": "अपने वर्कफ़्लो में सीधे अनुमोदन चेकपॉइंट बनाएं। महत्वपूर्ण क्रियाएं आगे बढ़ने से पहले मानवीय पुष्टि की प्रतीक्षा करती हैं।"}, "rollback": {"title": "रोलबैक और रिज़्यूम", "desc": "गलतियों का मतलब शुरू से शुरू करना नहीं है। चेकपॉइंट पर वापस जाएं, समस्या ठीक करें, और जहां छोड़ा वहां से जारी रखें।"}, "titleHighlight": "एक साथ डिज़ाइन करना चाहिए", "builtin": {"title": "बिल्ट-इन वैलिडेशन", "desc": "डेटा वैलिडेशन एक ऐड-ऑन नहीं है। हर मॉड्यूल इनपुट और आउटपुट को मान्य करता है। खराब डेटा स्पष्ट त्रुटि संदेशों के साथ वर्कफ़्लो को तुरंत रोक देता है।"}, "offline": {"title": "100% ऑफ़लाइन", "desc": "कोई क्लाउड निर्भरता नहीं। कोई फ़ोनिंग होम नहीं। पूर्ण डेटा संप्रभुता के साथ अपने इंफ्रास्ट्रक्चर पर डिप्लॉय करें।"}, "audit": {"title": "पूर्ण ऑडिट ट्रेल", "desc": "हर क्रिया में स्क्रीनशॉट, लॉग और टाइमस्टैम्प हैं। जानें कि वास्तव में क्या हुआ, कब, और किसने अनुमोदित किया। अनुपालन के लिए उत्तम।"}, "pause": {"title": "कभी भी रोकें", "desc": "हर वर्कफ़्लो मानवीय समीक्षा के लिए रुक सकता है। एक चलाएं, पुष्टि करें कि यह सही है, फिर बैच प्रोसेसिंग जारी रखें। कोई अंधा ऑटोमेशन नहीं।"}, "subtitle": "Flyto2 'ऑटोमेशन लॉजिक' और 'यूज़र इंटरैक्शन' के बीच अंतर नहीं करता। वे एक ही चीज़ हैं।", "title": "वर्कफ़्लो और इंटरफ़ेस को क्यों"}, "hero": {"titleHighlight": "बेकाबू नहीं होगा", "description": "पारंपरिक RPA विफल होता है जब मानवीय निर्णय की आवश्यकता होती है। Flyto2 मानवीय निरीक्षण को पहले दिन से मूल सुविधा बनाता है, बाद में सोचने का काम नहीं।", "title": "एक वर्कफ़्लो प्लेटफ़ॉर्म जो"}, "cta": {"description": "मुफ़्त में शुरू करें। क्रेडिट कार्ड की आवश्यकता नहीं। ऑफ़लाइन काम करता है।", "title": "ह्यूमन-इन-द-लूप ऑटोमेशन अनुभव करने के लिए तैयार?"}}, "buyoffline": {"card": {"unlimitedWorkflows": "असीमित वर्कफ़्लो", "checkpointResume": "चेकपॉइंट और रिज़्यूम", "prioritySupport": "प्राथमिकता सपोर्ट"}, "fingerprint": {"description": "आपका लाइसेंस इस मशीन से लॉक होगा। Flyto2 ऐप से फ़िंगरप्रिंट प्राप्त करें।", "howToTitle": "अपना फ़िंगरप्रिंट कैसे प्राप्त करें:", "howToDesc": "Flyto2 खोलें → सेटिंग्स → लाइसेंस → \"मशीन फ़िंगरप्रिंट कॉपी करें\" पर क्लिक करें", "pasteHere": "नीचे अपना मशीन फ़िंगरप्रिंट पेस्ट करें", "title": "मशीन फ़िंगरप्रिंट"}, "hero": {"featureNoInternet": "इंटरनेट आवश्यक नहीं", "featurePrivacy": "गोपनीयता पहले", "featureUpdates": "1 वर्ष अपडेट", "description": "इंटरनेट के बिना काम करें। आपका डेटा 100% आपकी मशीन पर रहता है।", "badge": "लाइफटाइम लाइसेंस", "title": "Pro Offline लाइसेंस"}, "billing": {"selectCountry": "देश चुनें", "fullName": "पूरा नाम *", "company": "कंपनी (वैकल्पिक)", "country": "देश *", "email": "ईमेल *", "other": "अन्य", "title": "बिलिंग जानकारी"}, "success": {"howToActivate": "कैसे सक्रिय करें", "downloadBtn": "लाइसेंस फ़ाइल डाउनलोड करें", "emailSent": "एक प्रति भी भेजी गई है", "licenseId": "लाइसेंस ID:", "subtitle": "आपका Pro Offline लाइसेंस तैयार है।", "step5b": "फ़ाइल", "step1": "ऊपर लाइसेंस फ़ाइल डाउनलोड करें", "step2": "Flyto2 एप्लिकेशन खोलें", "step3": "यहां जाएं", "step4": "क्लिक करें", "step5": "डाउनलोड की गई चुनें", "step6": "हो गया! Pro Offline सुविधाओं का आनंद लें।", "title": "भुगतान सफल!"}, "step1": {"licenseLinked": "आसान प्रबंधन के लिए आपका लाइसेंस इस खाते से लिंक होगा।", "continueBtn": "भुगतान पर जारी रखें", "signInTitle": "जारी रखने के लिए साइन इन करें", "signInDesc": "अपना लाइसेंस खरीदने और प्रबंधित करने के लिए कृपया हेडर में बटन का उपयोग करके साइन इन करें।", "signedInAs": "के रूप में साइन इन"}, "payment": {"securedBy": "Stripe द्वारा सुरक्षित। हम कभी भी आपके कार्ड विवरण संग्रहीत नहीं करते।", "title": "भुगतान"}, "steps": {"fingerprint": "फ़िंगरप्रिंट", "download": "डाउनलोड", "payment": "भुगतान"}, "plan": {"feature1": "वर्कफ़्लो रिकॉर्ड और प्लेबैक करें", "feature2": "100% ऑफ़लाइन काम करता है", "feature3": "असीमित वर्कफ़्लो", "feature4": "चेकपॉइंट और रिज़्यूम", "feature5": "1 वर्ष अपडेट शामिल", "title": "Pro Offline लाइसेंस"}, "step2": {"backBtn": "वापस", "payBtn": "भुगतान करें"}}, "download": {"docker": {"infrastructureDesc": "किसी भी क्लाउड प्रोवाइडर या बेयर मेटल सर्वर पर चलाएं। आप डेटा नियंत्रित करते हैं।", "autoUpdatesDesc": "Docker Watchtower सपोर्ट के साथ स्वचालित कंटेनर अपडेट।", "enterpriseDesc": "SSL/TLS और प्रमाणीकरण सपोर्ट के साथ प्रोडक्शन-ग्रेड सुरक्षा।", "infrastructure": "आपका इंफ्रास्ट्रक्चर", "getProLicense": "Pro लाइसेंस प्राप्त करें", "autoUpdates": "ऑटो अपडेट", "dockerDocs": "Docker डॉक्स", "enterprise": "एंटरप्राइज़ रेडी", "subtitle": "Docker के साथ अपने इंफ्रास्ट्रक्चर पर Flyto2 Pro डिप्लॉय करें", "title": "सेल्फ़-होस्टेड डिप्लॉयमेंट"}, "subscribe": {"releaseNotes": "केवल रिलीज़ नोट्स", "unsubscribe": "कभी भी अनसब्सक्राइब करें", "subtitle": "जब हम नए संस्करण और सुविधाएं रिलीज़ करें तो सबसे पहले जानें।", "button": "सदस्यता लें", "noSpam": "कभी स्पैम नहीं", "title": "अपडेट नोटिफिकेशन प्राप्त करें"}, "why": {"crossPlatformDesc": "Windows, macOS, और Linux पर बिना संशोधन के काम करता है। एक कोडबेस, हर जगह।", "crossPlatform": "क्रॉस प्लेटफ़ॉर्म", "offlineDesc": "इंस्टॉलेशन के बाद इंटरनेट की आवश्यकता नहीं। आपका डेटा लोकल और निजी रहता है।", "pythonDesc": "पूर्ण टाइप हिंट्स और async सपोर्ट के साथ आधुनिक Python के लिए बनाया गया। साफ़, पठनीय कोड।", "subtitle": "सादगी और नियंत्रण को महत्व देने वाले डेवलपर्स के लिए बनाया गया", "offline": "ऑफ़लाइन काम करता है", "python": "Python 3.9+", "title": "Flyto2 Core क्यों चुनें?"}, "hero": {"downloadLatest": "नवीनतम डाउनलोड करें", "viewSource": "सोर्स देखें", "subtitle": "ओपन सोर्स ऑटोमेशन इंजन। ऑफ़लाइन काम करता है, क्लाउड की आवश्यकता नहीं।", "title": "Flyto2 Core डाउनलोड करें"}, "versions": {"subtitle": "अपना पसंदीदा संस्करण चुनें या नवीनतम प्राप्त करें", "loading": "PyPI से संस्करण लोड हो रहे हैं...", "title": "सभी संस्करण"}}, "useCases": {"industries": {"manufacturing": "विनिर्माण", "government": "सरकार", "healthcare": "स्वास्थ्य सेवा", "education": "शिक्षा", "logistics": "लॉजिस्टिक्स", "subtitle": "कोई भी वर्कफ़्लो जिसे मानवीय निरीक्षण और ऑडिट ट्रेल की आवश्यकता है", "finance": "वित्त और बैंकिंग", "retail": "खुदरा और ई-कॉमर्स", "legal": "कानूनी", "title": "Flyto2 का उपयोग करने वाले उद्योग"}, "tags": {"dataClassification": "डेटा वर्गीकरण", "documentProcessing": "दस्तावेज़ प्रोसेसिंग", "exceptionHandling": "अपवाद हैंडलिंग", "anomalyDetection": "विसंगति पहचान", "qualityControl": "गुणवत्ता नियंत्रण", "internalTools": "आंतरिक टूल्स", "legacySystems": "लेगेसी सिस्टम", "procurement": "खरीद", "compliance": "अनुपालन", "dataEntry": "डेटा एंट्री", "finance": "वित्त", "noApi": "कोई API नहीं", "hr": "मानव संसाधन"}, "approval": {"result1": {"title": "80% तेज़ प्रोसेसिंग", "desc": "मानक अनुमोदन दिनों से घंटों में"}, "result2": {"title": "100% ऑडिट अनुपालन", "desc": "हर क्रिया टाइमस्टैम्प की गई"}, "result3": {"title": "त्रुटियों पर शून्य डेटा हानि", "desc": "चेकपॉइंट पर वापस जाएं, ठीक करें, जारी रखें"}, "result4": {"title": "मानवीय निरीक्षण संरक्षित", "desc": "महत्वपूर्ण निर्णय अभी भी मनुष्यों द्वारा लिए जाते हैं"}, "quoteAuthor": "- एंटरप्राइज़ फाइनेंस टीम", "step1": {"label": "ट्रिगर:", "text": "नया खरीद अनुरोध सबमिट किया गया"}, "step2": {"label": "मान्य करें:", "text": "बजट, वेंडर स्थिति, अनुमोदन सीमाएं जांचें"}, "step3": {"label": "मानव चरण:", "text": "अनुमोदन के लिए प्रबंधक को रूट करें"}, "step4": {"label": "स्वचालित करें:", "text": "PO बनाएं, वेंडर को सूचित करें, ERP अपडेट करें"}, "step5": {"label": "ऑडिट:", "text": "प्रत्येक चरण का स्क्रीनशॉट, सभी निर्णय लॉग करें"}, "subtitle": "अनुपालन के लिए ऑडिट ट्रेल के साथ मल्टी-स्टेप अनुमोदन फ़्लो", "problem": "पारंपरिक ऑटोमेशन अनुमोदन के लिए नहीं रुक सकता। खरीद आदेश, व्यय रिपोर्ट और अनुबंधों को प्रबंधक साइन-ऑफ की आवश्यकता होती है, लेकिन RPA टूल्स बस आगे बढ़ते जाते हैं।", "quote": "\"हमने 200+ अनुमोदन वर्कफ़्लो स्वचालित किए जबकि अनुपालन के लिए आवश्यक मानवीय निर्णय बनाए रखा।\"", "title": "एंटरप्राइज़ अनुमोदन वर्कफ़्लो", "tag": "सबसे लोकप्रिय"}, "hero": {"titleHighlight": "वर्कफ़्लो ऑटोमेशन", "description": "देखें कि एंटरप्राइज़ कैसे Flyto2 का उपयोग जटिल वर्कफ़्लो को स्वचालित करने के लिए करते हैं जिन्हें मानवीय निर्णय, अनुमोदन चरण और पूर्ण ऑडिट ट्रेल की आवश्यकता होती है।", "title": "वास्तविक दुनिया"}, "rpa": {"migration": {"title": "माइग्रेशन पथ", "desc": "पहले से UiPath, Blue Prism, या Automation Anywhere में निवेश किया? यहां बताया गया है कि Flyto2 आपके मौजूदा सेटअप को कैसे पूरक करता है (बदलता नहीं):"}, "flytoApproach": "Flyto2 दृष्टिकोण", "approach1": "प्रदर्शन द्वारा वर्कफ़्लो रिकॉर्ड करें", "approach2": "1 चलाएं, मान्य करें, फिर बैच", "approach3": "वैलिडेशन विफलताओं पर ऑटो-रोकें", "approach4": "ऑडिट के लिए हर क्रिया का स्क्रीनशॉट", "useFlyto1": "मानवीय अनुमोदन की आवश्यकता वाले वर्कफ़्लो", "useFlyto2": "ऑफ़लाइन/एयर-गैप्ड वातावरण", "useFlyto3": "एंटरप्राइज़ रोलआउट से पहले त्वरित प्रोटोटाइप", "useFlyto4": "बार-बार बदलते UI वाली प्रक्रियाएं", "keepRpa1": "उच्च-मात्रा, स्थिर प्रक्रियाएं", "keepRpa2": "मौजूदा ऑर्केस्ट्रेशन के साथ वर्कफ़्लो", "keepRpa3": "प्रक्रियाएं जिन्हें अनुमोदन की आवश्यकता नहीं", "subtitle": "जब आपके सिस्टम में API नहीं हैं लेकिन आपको ऑटोमेशन चाहिए", "useFlyto": "Flyto2 का उपयोग करें:", "whyFails": "पारंपरिक RPA यहां क्यों विफल होता है", "keepRpa": "अपने मौजूदा RPA का उपयोग जारी रखें:", "problem": "आपके आंतरिक एडमिन पोर्टल में कोई API नहीं है। आपका ERP 2005 का है। आपका वेंडर पोर्टल केवल Internet Explorer में काम करता है। आप IT के इंटीग्रेशन बनाने के लिए वर्षों का इंतज़ार नहीं कर सकते।", "fail1": "UI बदलने पर भंगुर", "fail2": "जारी रखने से पहले मान्य नहीं कर सकता", "fail3": "त्रुटियां पूरे बैच में फैलती हैं", "fail4": "अनुपालन के लिए कोई ऑडिट ट्रेल नहीं", "title": "आंतरिक टूल्स के लिए RPA बदलें"}, "hitl": {"insight": {"title": "मुख्य अंतर्दृष्टि", "desc": "सबसे अच्छा ऑटोमेशन पूरी तरह से स्वचालित नहीं है। यह ऑटोमेशन है जो अपनी सीमाएं जानता है और ज़रूरत होने पर मदद मांगता है।"}, "step1": {"label": "बैच:", "text": "प्रोसेसिंग के लिए 1,000 रिकॉर्ड लोड करें"}, "step2": {"label": "मान्य करें:", "text": "प्रत्येक रिकॉर्ड को नियमों के खिलाफ जांचें"}, "step3": {"label": "अपवाद रोकें:", "text": "असामान्य राशियां, गायब डेटा, डुप्लिकेट फ्लैग करें"}, "step4": {"label": "मानव समीक्षा:", "text": "ऑपरेटर समीक्षा करता है और फ्लैग किए गए आइटम को अनुमोदित/अस्वीकार करता है"}, "step5": {"label": "जारी रखें:", "text": "अनुमोदित आइटम प्रोसेस करें, अस्वीकृत छोड़ें"}, "whenToUse": "ह्यूमन-इन-द-लूप कब उपयोग करें", "subtitle": "ऑटोमेशन जो सत्यापन के लिए महत्वपूर्ण क्षणों पर रुकता है", "problem": "ऑटोमेशन 95% मामलों के लिए बढ़िया काम करता है। लेकिन वह 5% एज केस स्वचालित रूप से संभाले जाने पर भारी नुकसान कर सकता है। आपको ऐसा ऑटोमेशन चाहिए जो जानता हो कि कब रुकना है और पूछना है।", "title": "ह्यूमन-इन-द-लूप ऑटोमेशन", "when1": "सीमा से ऊपर उच्च-मूल्य लेनदेन", "when2": "डेटा जो अपेक्षित पैटर्न से मेल नहीं खाता", "when3": "पहली बार वेंडर या ग्राहक इंटरैक्शन", "when4": "विनियामक-संवेदनशील ऑपरेशन", "when5": "कोई भी क्रिया जिसे पूर्ववत करना कठिन है"}, "ai": {"balance": {"title": "सही संतुलन", "desc": "AI को मानवीय क्षमताओं को बढ़ाना चाहिए, मानवीय निर्णय को प्रतिस्थापित नहीं करना चाहिए। Flyto2 इस सिद्धांत के साथ इसके मूल में डिज़ाइन किया गया है।"}, "approachDesc": "AI शक्तिशाली है लेकिन अचूक नहीं। Flyto2 आपको सुझावों और विश्लेषण के लिए AI का लाभ उठाने देता है जबकि अंतिम निर्णयों में मनुष्यों को नियंत्रण में रखता है।", "step1": {"label": "इनपुट:", "text": "स्कैन किया गया इनवॉइस आता है"}, "step2": {"label": "AI:", "text": "वेंडर, राशि, लाइन आइटम, देय तिथि निकालें"}, "step3": {"label": "विश्वास:", "text": "कम-विश्वास निष्कर्षण फ्लैग करें"}, "step4": {"label": "मानव:", "text": "फ्लैग किए गए आइटम समीक्षा करें, ज़रूरत हो तो सही करें"}, "step5": {"label": "प्रोसेस:", "text": "AP एंट्री बनाएं, अनुमोदन के लिए रूट करें"}, "humanDoes1": "अंतिम अनुमोदन निर्णय", "humanDoes2": "अपवाद हैंडलिंग", "humanDoes3": "गुणवत्ता सत्यापन", "humanDoes4": "अनुपालन साइन-ऑफ", "humanDoes": "मनुष्य संभालते हैं:", "approach": "दृष्टिकोण", "subtitle": "AI को सुझाने दें, मनुष्यों को निर्णय लेने दें", "aiDoes1": "पैटर्न पहचान", "aiDoes2": "डेटा निष्कर्षण", "aiDoes3": "विसंगति पहचान", "aiDoes4": "वर्गीकरण सुझाव", "example": "उदाहरण: इनवॉइस प्रोसेसिंग", "aiDoes": "AI संभालता है:", "title": "AI-सहायित ऑपरेशन वर्कफ़्लो"}, "common": {"solution": "Flyto2 समाधान", "problem": "समस्या", "results": "परिणाम"}, "cta": {"description": "अपनी विशिष्ट वर्कफ़्लो चुनौतियों के बारे में हमसे बात करें। हम दिखाएंगे कि Flyto2 कैसे मदद कर सकता है।", "title": "कौन सा उपयोग मामला आपकी ज़रूरतों के अनुकूल है?"}}, "languagepacks": {"available": {"subtitle": "ऑफ़लाइन भाषा पैक डाउनलोड और इंस्टॉल करें", "loading": "उपलब्ध भाषा पैक लोड हो रहे हैं...", "title": "उपलब्ध भाषा पैक"}, "hero": {"description": "Flyto2 में ऑफ़लाइन उपयोग के लिए अनुवाद फ़ाइलें डाउनलोड करें", "title": "भाषा पैक"}, "request": {"feature1": "समुदाय-संचालित अनुवाद", "feature2": "नियमित अपडेट", "subtitle": "अपनी भाषा नहीं दिख रही? हमें बताएं!", "title": "भाषा अनुरोध करें", "btn": "भाषा अनुरोध करें"}, "howto": {"step1": "भाषा पैक फ़ाइल (.json) डाउनलोड करें", "step2": "Flyto2 एप्लिकेशन खोलें", "step3": "सेटिंग्स → भाषा पर जाएं", "step4": "\"भाषा पैक आयात करें\" पर क्लिक करें और फ़ाइल चुनें", "title": "कैसे इंस्टॉल करें"}}, "common": {"footer": {"allRightsReserved": "सर्वाधिकार सुरक्षित", "contributing": "योगदान", "openSource": "ओपन सोर्स", "philosophy": "दर्शन", "changelog": "चेंजलॉग", "copyright": "कॉपीराइट ©2025 Flyto2. सर्वाधिकार सुरक्षित", "download": "डाउनलोड", "company": "कंपनी", "contact": "संपर्क", "license": "लाइसेंस", "product": "उत्पाद", "tagline": "ऑटोमेशन जो आपकी तरह काम करता है। एक बार रिकॉर्ड करें, हमेशा के लिए रीप्ले करें।", "about": "के बारे में"}, "nav": {"plansAndPricing": "योजनाएं और मूल्य", "buyProLicense": "Pro लाइसेंस खरीदें", "documentation": "दस्तावेज़ीकरण", "languagePacks": "भाषा पैक", "flytoAccount": "Flyto2 खाता", "viewPricing": "मूल्य देखें", "desktopApp": "डेस्कटॉप ऐप", "myLicenses": "मेरे लाइसेंस", "philosophy": "दर्शन", "contactUs": "संपर्क करें", "resources": "संसाधन", "download": "डाउनलोड", "flytoCli": "Flyto Core (CLI)", "platform": "प्लेटफ़ॉर्म", "useCases": "उपयोग के मामले", "compare": "तुलना", "contact": "संपर्क", "pricing": "मूल्य", "signOut": "साइन आउट", "signIn": "साइन इन", "about": "के बारे में", "blog": "ब्लॉग", "home": "होम", "faq": "FAQ"}, "cta": {"getStartedFree": "मुफ़्त शुरू करें", "noCreditCard": "क्रेडिट कार्ड की आवश्यकता नहीं", "worksOffline": "ऑफ़लाइन काम करता है", "viewPricing": "मूल्य देखें"}, "auth": {"flytoAccount": "Flyto2 खाता", "myLicenses": "मेरे लाइसेंस", "signOut": "साइन आउट", "signIn": "साइन इन"}}, "compare": {"notRight": {"titleHighlight": "नहीं है", "choose1": {"title": "मानवीय अनुमोदन आपके वर्कफ़्लो का हिस्सा है", "desc": "बिल्ट-इन, बोल्ट-ऑन नहीं मानवीय निरीक्षण"}, "choose2": {"title": "आपको ऑफ़लाइन/एयर-गैप्ड डिप्लॉयमेंट चाहिए", "desc": "100% लोकल एक्जीक्यूशन, कोई क्लाउड निर्भरता नहीं"}, "choose3": {"title": "ऑडिट ट्रेल अनिवार्य हैं", "desc": "हर क्रिया के लिए स्क्रीनशॉट और लॉग"}, "choose4": {"title": "आप पूर्ण बैच से पहले टेस्ट-रन करना चाहते हैं", "desc": "एक चलाएं, सत्यापित करें, फिर बैच - सुरक्षित रूप से"}, "skip1": {"title": "आपको 100+ बॉट एक साथ चलाने हैं", "desc": "UiPath या Automation Anywhere के पास बेहतर ऑर्केस्ट्रेशन है"}, "skip2": {"title": "आपको केवल API इंटीग्रेशन चाहिए", "desc": "n8n, Zapier, या Make केवल-API वर्कफ़्लो के लिए सरल हैं"}, "skip3": {"title": "आप पूर्ण अनअटेंडेड ऑटोमेशन चाहते हैं", "desc": "Flyto2 मानवीय निरीक्षण के लिए बना है; अगर आपको इसकी ज़रूरत नहीं, यह ओवरहेड है"}, "skip4": {"title": "आपके पास बड़े मौजूदा RPA निवेश हैं", "desc": "अपने मौजूदा प्लेटफ़ॉर्म को विस्तारित करना अधिक लागत प्रभावी हो सकता है"}, "subtitle": "हम ईमानदार पोज़िशनिंग में विश्वास करते हैं। यहां बताया गया है कि आपको कब कहीं और देखना चाहिए।", "titleEnd": "सही विकल्प", "choose": "Flyto2 चुनें अगर...", "title": "जब Flyto2", "skip": "Flyto2 छोड़ें अगर..."}, "summary": {"titleHighlight": "अवलोकन", "uipath": {"item1": "बड़े पैमाने पर डिप्लॉयमेंट (1000+ बॉट)", "item2": "मौजूदा RPA इंफ्रास्ट्रक्चर", "item3": "समर्पित RPA टीम", "item4": "एंटरप्राइज़ लाइसेंसिंग बजट", "title": "एंटरप्राइज़-स्केल RPA", "tag": "UiPath चुनें इसके लिए"}, "flyto": {"item1": "अनुमोदन वर्कफ़्लो", "item2": "ऑफ़लाइन/एयर-गैप्ड डिप्लॉयमेंट", "item3": "पूर्ण ऑडिट ट्रेल आवश्यक", "item4": "वर्कफ़्लो रोकें और सत्यापित करें", "title": "मानवीय निरीक्षण ज़रूरतें", "tag": "Flyto2 चुनें इसके लिए"}, "n8n": {"item1": "SaaS ऐप्स कनेक्ट करना", "item2": "Webhook-आधारित ट्रिगर", "item3": "डेवलपर-फ़्रेंडली वर्कफ़्लो", "item4": "सेल्फ़-होस्टेड विकल्प चाहिए", "title": "API इंटीग्रेशन फ़ोकस", "tag": "n8n चुनें इसके लिए"}, "subtitle": "विभिन्न ज़रूरतों के लिए विभिन्न टूल। यहां बताया गया है कि कौन सा कब चुनें।", "title": "त्वरित"}, "hero": {"titleHighlight": "अलग", "description": "देखें कि Flyto2 अन्य वर्कफ़्लो ऑटोमेशन प्लेटफ़ॉर्म से कैसे तुलना करता है। हम मानवीय निरीक्षण, ऑफ़लाइन क्षमता और एंटरप्राइज़ अनुपालन पर ध्यान केंद्रित करते हैं।", "title": "Flyto2 कैसे है"}, "cta": {"description": "मुफ़्त में शुरू करें। क्रेडिट कार्ड की आवश्यकता नहीं। मानवीय निरीक्षण का अंतर अनुभव करें।", "talkToUs": "हमसे बात करें", "title": "Flyto2 आज़माने के लिए तैयार?"}}, "index": {"counter": {"replayForeverDesc": "अलग डेटा के साथ फिर से चलाएं। सैकड़ों आइटम बैच प्रोसेस करें।", "stayInControlDesc": "कभी भी रोकें, सत्यापित करें और फिर से शुरू करें। रनअवे ऑटोमेशन की चिंता कभी न करें।", "recordOnceDesc": "Flyto2 को दिखाएं कि आप कैसे काम करते हैं। यह आपके क्लिक और कीस्ट्रोक देखकर सीखता है।", "replayForever": "हमेशा के लिए रीप्ले करें", "stayInControl": "नियंत्रण में रहें", "recordOnce": "एक बार रिकॉर्ड करें"}, "hero": {"titleHighlight": "ऑटोमेशन जो करता है", "description": "Flyto2 एक ऑटोमेशन टूल है जो आपके कंप्यूटर को इंसान की तरह संचालित करता है। ब्राउज़र खोलें, बटन क्लिक करें, फ़ॉर्म भरें, फ़ाइलें अपलोड करें। आप एक बार करें, Flyto2 हमेशा के लिए दोहराता है।", "titleEnd": "जो आप दिखाते हैं"}, "why": {"subtitle": "कई कार्य कठिन नहीं हैं, वे बस थकाऊ हैं।", "title": "क्यों"}}, "blog": {"categories": {"designPatterns": "डिज़ाइन पैटर्न", "architecture": "आर्किटेक्चर", "rpaFailures": "RPA विफलताएं", "allPosts": "सभी पोस्ट"}, "newsletter": {"description": "नवीनतम ऑटोमेशन अंतर्दृष्टि और उत्पाद अपडेट के लिए हमारे न्यूज़लेटर की सदस्यता लें।", "subscribe": "सदस्यता लें", "noSpam": "कोई स्पैम नहीं। कभी भी अनसब्सक्राइब करें।", "title": "अपडेट रहें"}, "latestArticles": {"title": "नवीनतम लेख"}, "posts": {"post1": {"readTime": "6 मिनट पढ़ें", "excerpt": "ऑटोमेशन दक्षता का त्याग किए बिना मानवीय सत्यापन की आवश्यकता वाले वर्कफ़्लो कैसे बनाएं।", "title": "रुकने योग्य वर्कफ़्लो डिज़ाइन करना"}, "post2": {"readTime": "5 मिनट पढ़ें", "excerpt": "आपके ऑटोमेशन टूल्स को इंटरनेट कनेक्शन की आवश्यकता क्यों नहीं होनी चाहिए, और इसे कैसे करें।", "title": "ऑफ़लाइन-फर्स्ट ऑटोमेशन का मामला"}, "post3": {"readTime": "10 मिनट पढ़ें", "excerpt": "एक एंटरप्राइज़ ने पारंपरिक RPA से ह्यूमन-इन-द-लूप वर्कफ़्लो में कैसे माइग्रेट किया।", "title": "UiPath से Flyto2: एक माइग्रेशन कहानी"}, "post4": {"readTime": "7 मिनट पढ़ें", "excerpt": "बेसिक लॉगिंग से आगे जाकर ऑडिट ट्रेल बनाना जो वास्तव में अनुपालन के लिए मायने रखते हैं।", "title": "वास्तव में काम करने वाले ऑडिट ट्रेल बनाना"}, "post5": {"readTime": "6 मिनट पढ़ें", "excerpt": "पूरे बैच विफलताओं से बचने के लिए हर चरण पर डेटा सत्यापन के पैटर्न।", "title": "एंटरप्राइज़ वर्कफ़्लो के लिए वैलिडेशन पैटर्न"}, "post6": {"readTime": "4 मिनट पढ़ें", "excerpt": "नवीनतम रिलीज़ में नई सुविधाएं, सुधार और बग फ़िक्स एक्सप्लोर करें।", "title": "Flyto2 v2.0 में नया क्या है"}}, "featured": {"readTime": "8 मिनट पढ़ें", "excerpt": "अधिकांश RPA टूल्स उन वर्कफ़्लो के अनुकूल क्यों नहीं हो पाते जिन्हें मानवीय अनुमोदन, सत्यापन या निरीक्षण की आवश्यकता होती है।", "badge": "विशेष", "title": "पारंपरिक RPA ह्यूमन-इन-द-लूप में क्यों विफल होता है"}, "hero": {"description": "एंटरप्राइज़ वर्कफ़्लो ऑटोमेशन, ह्यूमन-इन-द-लूप डिज़ाइन पैटर्न और आर्किटेक्चर बेस्ट प्रैक्टिस पर अंतर्दृष्टि।", "title": "ब्लॉग"}, "cta": {"description": "मुफ़्त में शुरू करें। क्रेडिट कार्ड की आवश्यकता नहीं। ह्यूमन-इन-द-लूप ऑटोमेशन का अनुभव करें।", "button": "मुफ़्त शुरू करें", "title": "Flyto2 आज़माने के लिए तैयार?"}, "comingSoon": "जल्द आ रहा है"}, "contact": {"quickLinks": {"subtitle": "सामान्य सवालों के जवाब खोजें", "title": "त्वरित लिंक"}, "cards": {"community": "समुदाय", "emailUs": "हमें ईमेल करें", "github": "GitHub"}, "cta": {"downloadNow": "अभी डाउनलोड करें", "subtitle": "आज ही अपने वर्कफ़्लो को स्वचालित करना शुरू करें", "title": "शुरू करने के लिए तैयार?"}, "form": {"subtitle": "फ़ॉर्म भरें और हम आपसे संपर्क करेंगे", "title": "हमें संदेश भेजें"}, "hero": {"subtitle": "सवाल हैं? हम आपसे सुनना पसंद करेंगे।", "title": "संपर्क करें"}}, "faq": {"gettingStarted": {"subtitle": "Flyto2 का उपयोग कैसे शुरू करें", "title": "शुरू करना"}, "cta": {"contactSupport": "सपोर्ट से संपर्क करें", "subtitle": "आप जो जवाब खोज रहे हैं वह नहीं मिला? हमारी टीम मदद के लिए यहां है।", "viewDocs": "दस्तावेज़ीकरण देखें", "title": "अभी भी सवाल हैं?"}, "licensing": {"subtitle": "योजनाएं, मूल्य और लाइसेंस प्रबंधन", "title": "लाइसेंसिंग और मूल्य"}, "general": {"subtitle": "Flyto2 के बारे में बुनियादी बातें जानें", "title": "सामान्य सवाल"}, "hero": {"title": "अक्सर पूछे जाने वाले सवाल"}}, "pricing": {"offline": {"learnMore": "ऑफ़लाइन लाइसेंसिंग के बारे में और जानें", "step1": "ऑनलाइन लाइसेंस कुंजी खरीदें", "step2": "अपनी मशीन पर सक्रिय करें (एक बार इंटरनेट आवश्यक)", "step3": "लाइसेंस अवधि के लिए पूरी तरह से ऑफ़लाइन उपयोग करें", "step4": "अपडेट और सपोर्ट बढ़ाने के लिए कभी भी नवीनीकृत करें", "title": "ऑफ़लाइन लाइसेंस कैसे काम करते हैं"}, "section": {"subtitle": "ओपन सोर्स के साथ मुफ़्त शुरू करें, ज़रूरत होने पर अपग्रेड करें", "title": "अपनी योजना चुनें"}, "cta": {"talkToSales": "सेल्स से बात करें", "subtitle": "मुफ़्त संस्करण से शुरू करें या व्यक्तिगत सिफारिश के लिए हमसे संपर्क करें।", "tryFree": "मुफ़्त आज़माएं", "title": "कौन सी योजना चुनें?"}, "loadingPricing": "मूल्य लोड हो रहा है...", "hero": {"subtitle": "मुफ़्त शुरू करें, बढ़ने के साथ स्केल करें। कोई छिपी फीस नहीं।", "title": "अपनी योजना चुनें"}, "faq": {"title": "अक्सर पूछे जाने वाले सवाल", "a1": "हां, आप कभी भी अपनी क्लाउड योजना अपग्रेड या डाउनग्रेड कर सकते हैं। ऑफ़लाइन लाइसेंस के लिए, आप अंतर का भुगतान करके अपग्रेड कर सकते हैं।", "a2": "आपके वर्कफ़्लो अनिश्चित काल तक काम करते रहते हैं। आप केवल अपडेट और सपोर्ट तक पहुंच खो देते हैं। नवीनतम सुविधाएं प्राप्त करने के लिए कभी भी नवीनीकृत करें।", "a3": "हां, हम सभी पेड योजनाओं के लिए 30-दिन की मनी-बैक गारंटी प्रदान करते हैं। कोई सवाल नहीं पूछा जाएगा।", "a4": "बिल्कुल! ओपन सोर्स कोर MIT लाइसेंस प्राप्त है। आप इसे किसी भी उद्देश्य के लिए उपयोग कर सकते हैं, व्यावसायिक परियोजनाओं सहित।", "q1": "क्या मैं योजनाओं के बीच स्विच कर सकता हूं?", "q2": "जब मेरा ऑफ़लाइन लाइसेंस समाप्त होता है तो क्या होता है?", "q3": "क्या आप रिफंड देते हैं?", "q4": "क्या मैं मुफ़्त संस्करण का व्यावसायिक रूप से उपयोग कर सकता हूं?"}, "loading": "लोड हो रहा है..."}, "app": {"hero": {"detectingInfo": "डिटेक्ट हो रहा है...", "downloadFor": "अपने सिस्टम के लिए डाउनलोड करें", "detecting": "आपका सिस्टम डिटेक्ट हो रहा है...", "subtitle": "अपने ब्राउज़र वर्कफ़्लो को स्वचालित करें। ऑफ़लाइन काम करता है, आपका डेटा निजी रहता है।", "proNote": "मुफ़्त डाउनलोड। पूर्ण सुविधाओं के लिए Pro लाइसेंस आवश्यक।", "title": "Flyto2 डाउनलोड करें"}, "platforms": {"subtitle": "अपना ऑपरेटिंग सिस्टम और आर्किटेक्चर चुनें", "title": "सभी प्लेटफ़ॉर्म"}, "requirements": {"title": "सिस्टम आवश्यकताएं"}, "install": {"step1Desc": "ऊपर अपने ऑपरेटिंग सिस्टम के लिए संस्करण चुनें", "step2Desc": "डाउनलोड की गई फ़ाइल पर डबल-क्लिक करें और निर्देशों का पालन करें", "step3Desc": "ऐप खोलें और अपने वर्कफ़्लो को स्वचालित करना शुरू करें", "step4Desc": "सभी सुविधाएं अनलॉक करने के लिए अपनी लाइसेंस फ़ाइल आयात करें", "subtitle": "कुछ ही मिनटों में शुरू करें", "step1": "इंस्टॉलर डाउनलोड करें", "step2": "इंस्टॉलर चलाएं", "step3": "Flyto2 लॉन्च करें", "step4": "Pro सक्रिय करें (वैकल्पिक)", "title": "इंस्टॉलेशन गाइड"}}}, "common": {"ports": {"error": "आउटपुट"}}}}